pysisnoapi/__init__.py
pysisnoapi/misc.py
pysisnoapi/nfe.py
pysisnoapi/nfse.py
pysisnoapi-0.2.2.dist-info/LICENSE.md
pysisnoapi-0.2.2.dist-info/METADATA
pysisnoapi-0.2.2.dist-info/WHEEL
pysisnoapi-0.2.2.dist-info/RECORD
