Metadata-Version: 2.1
Name: pysisnoapi
Version: 0.2.2
Summary: Wrapper para API da plataforma SISNO.
License: MIT
Author: Vinícius Costa
Author-email: viniciusccosta95@gmail.com
Requires-Python: >=3.11,<4.0
Classifier: License :: OSI Approved :: MIT License
Classifier: Programming Language :: Python :: 3
Classifier: Programming Language :: Python :: 3.11
Requires-Dist: httpx (>=0.25.0,<0.26.0)
Requires-Dist: jsonpickle (>=3.0.1,<4.0.0)
Requires-Dist: python-dateutil (>=2.8.2,<3.0.0)
Requires-Dist: requests (>=2.31.0,<3.0.0)
